avlautomation/__init__.py
avlautomation/aero.py
avlautomation/avlautomation.py
avlautomation/dihedral.py
avlautomation/geometry.py
avlautomation/tail.py
avlautomation-1.0.2.dist-info/LICENSE
avlautomation-1.0.2.dist-info/METADATA
avlautomation-1.0.2.dist-info/WHEEL
avlautomation-1.0.2.dist-info/top_level.txt
avlautomation-1.0.2.dist-info/RECORD
