Metadata-Version: 2.1
Name: avlautomation
Version: 1.0.2
Summary: Automation tools for vortex lattice method, AVL
Home-page: https://github.com/Team-Peryton/AVL-automation
Author: jj-foster
Requires-Python: >=3.9
License-File: LICENSE
Requires-Dist: numpy
Requires-Dist: scipy
Requires-Dist: pandas
Requires-Dist: matplotlib
Requires-Dist: tqdm
